<Ui xmlns="http://www.blizzard.com/wow/ui/" xmlns:xsi="http://www.w3.org/2001/XMLSchema-instance" xsi:schemaLocation="http://www.blizzard.com/wow/ui/..\FrameXML\UI.xsd">
    <Script file="htmlview.lua"/>

<!-- 

-->
	<Frame virtual="true" name="Vendor_HtmlView" inherits="InsetFrameTemplate">
		<Frames>	
			<ScrollFrame parentKey="Scroll"  inherits="UIPanelScrollFrameTemplate">
				<KeyValues>
					<KeyValue key="containerPadding" value="8" type="number"/>
					<KeyValue key="adjustX" value="4" type="number"/>
					<KeyValue key="adjustY" value="4" type="number"/>
				</KeyValues>
				<Anchors>
					<Anchor point="TOPLEFT" x="8" y="-8"/>
					<Anchor point="BOTTOMRIGHT" x="8" y="8"/>
				</Anchors>
				<Layers>
					<Layer level="BACKGROUND">
						<Texture parentKey="Background">
							<Color r="0.1" g="0.1" b="0.1" a="0.50"/>
						</Texture>
					</Layer>
				</Layers>
				<ScrollChild>
					<SimpleHTML parentKey="Content">
						<Size x="316" y="100"/>
						<Anchors>
							<Anchor point="TOPLEFT"/>
							<Anchor point="TOPRIGHT"/>
						</Anchors>
						<FontString inherits="GameFontNormal" justifyH="LEFT" justifyV="TOP" spacing="4"/>
						<FontStringHeader1 inherits="GameFontHighlightLarge" spacing="8" justifyH="CENTER" justifyV="TOP"/>
						<FontStringHeader2 inherits="GameFontHighlight" spacing="4" justifyH="LEFT" justifyV="TOP"/>
						<FontStringHeader3 inherits="GameFontHighlight" spacing="4" justifyH="LEFT" justifyV="TOP"/>
					</SimpleHTML>
				</ScrollChild>
			</ScrollFrame>
		</Frames>
		<Scripts>
			<OnLoad>
				self.Implementation = "HtmlView";
				Vendor.LoadImplementation(self, "Controls");
			</OnLoad>
		</Scripts>
	</Frame>

</Ui>